mcpman/__init__.py
mcpman/__main__.py
mcpman/cli.py
mcpman/config.py
mcpman/formatting.py
mcpman/llm_client.py
mcpman/logger.py
mcpman/models.py
mcpman/orchestrator.py
mcpman/server.py
mcpman/tools.py
mcpman/llm_clients/__init__.py
mcpman/llm_clients/anthropic.py
mcpman/llm_clients/base.py
mcpman/llm_clients/openai_compat.py
mcpman/llm_clients/openai_responses.py
mcpman-0.3.6.dist-info/licenses/LICENSE
mcpman-0.3.6.dist-info/METADATA
mcpman-0.3.6.dist-info/WHEEL
mcpman-0.3.6.dist-info/entry_points.txt
mcpman-0.3.6.dist-info/top_level.txt
mcpman-0.3.6.dist-info/RECORD
