Metadata-Version: 2.4
Name: mcpman
Version: 0.3.6
Summary: Model Context Protocol (MCP) Manager - a tool for managing MCP servers
Author-email: Eric Florenzano <floguy@gmail.com>
License: Apache-2.0
Classifier: Programming Language :: Python :: 3
Classifier: License :: OSI Approved :: Apache Software License
Classifier: Operating System :: OS Independent
Requires-Python: >=3.10
License-File: LICENSE
Requires-Dist: httpx>=0.28.1
Requires-Dist: mcp>=1.7.1
Requires-Dist: colorama>=0.4.6
Requires-Dist: openai==1.77.0
Requires-Dist: anthropic==0.50.0
Provides-Extra: dev
Requires-Dist: black; extra == "dev"
Requires-Dist: isort; extra == "dev"
Requires-Dist: pytest>=7.0.0; extra == "dev"
Requires-Dist: pytest-asyncio; extra == "dev"
Dynamic: license-file
